{
  "starting_time": 10,
  "text": {"pos": [0, 5.5, -29.25], "rot": [0, 180, 0], "scale": 8},
  "time_bonus_mul": 1,

  "terrain": [
    {"path": "baluz:models/terrain/floor/model.obj", "pos": [0, 0, 0]},
    {"path": "baluz:models/terrain/torii/torii_gate.obj", "pos": [0, 0, 15]},
    {"path": "baluz:models/terrain/torii/torii_gate.obj", "pos": [15, 0, 0], "rot": 90},
    {"path": "baluz:models/terrain/torii/torii_gate.obj", "pos": [-15, 0, 0], "rot": -90},
    {"path": "baluz:models/terrain/score/model.obj", "pos": [0, 0, -30]}
  ],

  "waves": [
    {
      "awards": {"time": 30, "score": 10},
      "balloons": [ 
        {"material": "DEBUG", "pos": [-3, 0, -2]},
        {"material": "CRYSTAL", "pos": [-1, 0, -2]},
        {"material": "METAL_WEAVE", "pos": [2, 0, -2]},
        {"material": "GOLD", "pos": [4, 0, -2], "score": 1000}
      ]
    },

    {
      "awards": {"time": 5, "score": 100},
      "balloons": [ 
        {"color": "AD72FF", "pos": [-3, 2, -3.5]},
        {"color": "AD72FF", "pos": [-2, 2, -3.5]},
        {"color": "AD72FF", "pos": [-1, 2, -3.5]},
        {"color": "AD72FF", "pos": [0, 2, -3.5]},
        {"color": "AD72FF", "pos": [1, 2, -3.5]},
        {"color": "AD72FF", "pos": [2, 2, -3.5]},
        {"color": "AD72FF", "pos": [3, 2, -3.5]},
        {"color": "AD72FF", "pos": [4, 2, -3.5]}
      ]
    },

    {
      "awards": {"time": 0, "score": 0},
      "balloons": [ 
        {"pos": [0.5, 0, 3]},
        {"pos": [0.5, 0, 4]},
        {"pos": [0.5, 0, 5]},
        {"pos": [0.5, 0, 6]},
        {"pos": [0.5, 0, 7]}
      ]
    }
  ]
}